XinlingTanxian/Dockerfile
XinlingTanxian/README.md
XinlingTanxian/__init__.py
XinlingTanxian/__main__.py
XinlingTanxian/file.epub
XinlingTanxian/index.html
XinlingTanxian/css/__init__.py
XinlingTanxian/css/annotations.css
XinlingTanxian/css/main.css
XinlingTanxian/css/normalize.css
XinlingTanxian/css/popup.css
XinlingTanxian/font/__init__.py
XinlingTanxian/font/fontello.eot
XinlingTanxian/font/fontello.svg
XinlingTanxian/font/fontello.ttf
XinlingTanxian/font/fontello.woff
XinlingTanxian/img/__init__.py
XinlingTanxian/img/annotator-glyph-sprite.png
XinlingTanxian/img/annotator-icon-sprite.png
XinlingTanxian/img/apple-touch-icon.png
XinlingTanxian/img/cancelfullscreen.png
XinlingTanxian/img/close.png
XinlingTanxian/img/fullscreen.png
XinlingTanxian/img/loader.gif
XinlingTanxian/img/menu-icon.png
XinlingTanxian/img/save.png
XinlingTanxian/img/saved.png
XinlingTanxian/img/settings-s.png
XinlingTanxian/img/settings.png
XinlingTanxian/img/star.png
XinlingTanxian/js/__init__.py
XinlingTanxian/js/epub.js
XinlingTanxian/js/epub.min.js
XinlingTanxian/js/epub.min.map
XinlingTanxian/js/hooks.min.js
XinlingTanxian/js/hooks.min.map
XinlingTanxian/js/reader.js
XinlingTanxian/js/reader.js.map
XinlingTanxian/js/reader.min.js
XinlingTanxian/js/reader.min.map
XinlingTanxian/js/hooks/__init__.py
XinlingTanxian/js/hooks/extensions/__init__.py
XinlingTanxian/js/hooks/extensions/highlight.js
XinlingTanxian/js/libs/__init__.py
XinlingTanxian/js/libs/jquery.min.js
XinlingTanxian/js/libs/localforage.min.js
XinlingTanxian/js/libs/screenfull.js
XinlingTanxian/js/libs/screenfull.min.js
XinlingTanxian/js/libs/zip.min.js
XinlingTanxian/js/plugins/__init__.py
XinlingTanxian/js/plugins/hypothesis.js
XinlingTanxian/js/plugins/search.js
xinling_tanxian-2022.10.9.1.dist-info/METADATA
xinling_tanxian-2022.10.9.1.dist-info/WHEEL
xinling_tanxian-2022.10.9.1.dist-info/entry_points.txt
xinling_tanxian-2022.10.9.1.dist-info/top_level.txt
xinling_tanxian-2022.10.9.1.dist-info/RECORD
